vezzo/__init__.py
vezzo/exceptions.py
vezzo-1.0.1.dist-info/LICENSE
vezzo-1.0.1.dist-info/METADATA
vezzo-1.0.1.dist-info/WHEEL
vezzo-1.0.1.dist-info/RECORD
