Metadata-Version: 2.1
Name: vezzo
Version: 1.0.1
Summary: A small library to verify that compatible versions of dependencies are installed before your tool can run properly.
License: MIT
Author: Anders Goncalves da Silva
Author-email: andersgs@gmail.com
Requires-Python: >=3.10,<4.0
Classifier: License :: OSI Approved :: MIT License
Classifier: Programming Language :: Python :: 3
Classifier: Programming Language :: Python :: 3.10
Classifier: Programming Language :: Python :: 3.11
Requires-Dist: semver (>=2.13.0,<3.0.0)
